genhr/__init__.py
genhr/genhr.py
genhr/types.py
genhr-0.1.1.dist-info/WHEEL
genhr-0.1.1.dist-info/METADATA
genhr-0.1.1.dist-info/RECORD
